setup.py
rtmbot_mattermost/__init__.py
rtmbot_mattermost/core.py
rtmbot_mattermost.egg-info/PKG-INFO
rtmbot_mattermost.egg-info/SOURCES.txt
rtmbot_mattermost.egg-info/dependency_links.txt
rtmbot_mattermost.egg-info/entry_points.txt
rtmbot_mattermost.egg-info/requires.txt
rtmbot_mattermost.egg-info/top_level.txt
rtmbot_mattermost/bin/__init__.py
rtmbot_mattermost/bin/run_rtmbot.py
rtmbot_mattermost/utils/__init__.py
rtmbot_mattermost/utils/module_loading.py
rtmbot_mattermost/utils/parse.py