Metadata-Version: 1.0
Name: rtmbot-mattermost
Version: 0.5.2
Summary: A Mattermost bot written in python that connects via the RTM API.
Home-page: https://github.com/ShotaKitazawa/rtmbot-mattermost
Author: ShotaKitazawa
Author-email: skitazawa1121@gmail.com
License: UNKNOWN
Platform: UNKNOWN
